Calculator/__init__.py
Calculator/operations.py
kalkulator2_0-1.0.0.dist-info/METADATA
kalkulator2_0-1.0.0.dist-info/WHEEL
kalkulator2_0-1.0.0.dist-info/top_level.txt
kalkulator2_0-1.0.0.dist-info/RECORD
