Metadata-Version: 2.4
Name: Kalkulator2.0
Version: 1.0.0
Summary: A simple calculator package for practice
Home-page: 
Author: Victor
Author-email: 
Classifier: Programming Language :: Python :: 3
Classifier: License :: OSI Approved :: MIT License
Classifier: Operating System :: OS Independent
Requires-Python: >=3.6
Dynamic: author
Dynamic: classifier
Dynamic: description
Dynamic: description-content-type
Dynamic: requires-python
Dynamic: summary
